Metadata-Version: 1.0
Name: Rotten-API
Version: 0.1
Summary: Rotten Tomatoes API
Home-page: https://github.com/chyvn/Rotten_API
Author: Avinash Tulasi
Author-email: avinasht@iiitd.ac.in
License: MIT
Platform: UNKNOWN
